energy_mpc/__init__.py
energy_mpc/custom_simulations/__init__.py
energy_mpc/custom_simulations/conf.py
energy_mpc/custom_simulations/mpc.py
energy_mpc/custom_simulations/simulation.py
energy_mpc/custom_simulations/utils.py
energy_mpc/custom_simulations/models/__init__.py
energy_mpc/custom_simulations/models/base.py
energy_mpc/custom_simulations/models/battery.py
energy_mpc/custom_simulations/models/boiler.py
energy_mpc/custom_simulations/models/building.py
energy_mpc/custom_simulations/models/combined_heat_power.py
energy_mpc/custom_simulations/models/cooling_chambers.py
energy_mpc/custom_simulations/models/demand.py
energy_mpc/custom_simulations/models/distribution.py
energy_mpc/custom_simulations/models/energy_market.py
energy_mpc/custom_simulations/models/ev.py
energy_mpc/custom_simulations/models/gas_grid.py
energy_mpc/custom_simulations/models/group.py
energy_mpc/custom_simulations/models/heat_base.py
energy_mpc/custom_simulations/models/heat_pump.py
energy_mpc/custom_simulations/models/heat_storage.py
energy_mpc/custom_simulations/models/hydro.py
energy_mpc/custom_simulations/models/meta_components.py
energy_mpc/custom_simulations/models/power_grid.py
energy_mpc/custom_simulations/models/pv.py
energy_mpc/custom_simulations/models/refrigeration_system.py
energy_mpc/custom_simulations/models/utils.py
energy_mpc/custom_simulations/models/ventilation.py
energy_mpc/custom_simulations/models/tests/__init__.py
energy_mpc/custom_simulations/models/tests/test_base.py
energy_mpc/custom_simulations/models/tests/test_heat_pump.py
energy_mpc/custom_simulations/models/tests/test_models.py
energy_mpc/custom_simulations/models/tests/test_power_grid.py
energy_mpc/custom_simulations/models/tests/test_utils.py
simulation_mpc_core-0.2.8.dist-info/METADATA
simulation_mpc_core-0.2.8.dist-info/WHEEL
simulation_mpc_core-0.2.8.dist-info/top_level.txt
simulation_mpc_core-0.2.8.dist-info/RECORD
